<?xml version="1.0" encoding="UTF-8"?>
<!DOCTYPE mapper PUBLIC "-//mybatis.org//DTD Mapper 3.0//EN" "http://mybatis.org/dtd/mybatis-3-mapper.dtd">
<mapper namespace="com.unis.dao.mybatis.AdminMapper">
  <resultMap id="BaseResultMap" type="com.unis.model.Admin">
    <!--
      WARNING - @mbg.generated
      This element is automatically generated by MyBatis Generator, do not modify.
    -->
    <id column="name" jdbcType="VARCHAR" property="name" />
    <result column="password" jdbcType="VARCHAR" property="password" />
    <result column="pages" jdbcType="VARCHAR" property="pages" />
    <result column="channels" jdbcType="VARCHAR" property="channels" />
  </resultMap>
  <sql id="Base_Column_List">
    <!--
      WARNING - @mbg.generated
      This element is automatically generated by MyBatis Generator, do not modify.
    -->
    name, password, pages, channels
  </sql>
  <select id="selectByPrimaryKey" parameterType="java.lang.String" resultMap="BaseResultMap">
    <!--
      WARNING - @mbg.generated
      This element is automatically generated by MyBatis Generator, do not modify.
    -->
    select 
    <include refid="Base_Column_List" />
    from t_backend_admin
    where name = #{name,jdbcType=VARCHAR}
  </select>
  <delete id="deleteByPrimaryKey" parameterType="java.lang.String">
    <!--
      WARNING - @mbg.generated
      This element is automatically generated by MyBatis Generator, do not modify.
    -->
    delete from t_backend_admin
    where name = #{name,jdbcType=VARCHAR}
  </delete>
  <insert id="insert" parameterType="com.unis.model.Admin">
    <!--
      WARNING - @mbg.generated
      This element is automatically generated by MyBatis Generator, do not modify.
    -->
    insert into t_backend_admin (name, password, pages, 
      channels)
    values (#{name,jdbcType=VARCHAR}, #{password,jdbcType=VARCHAR}, #{pages,jdbcType=VARCHAR}, 
      #{channels,jdbcType=VARCHAR})
  </insert>
  <insert id="insertSelective" parameterType="com.unis.model.Admin">
    <!--
      WARNING - @mbg.generated
      This element is automatically generated by MyBatis Generator, do not modify.
    -->
    insert into t_backend_admin
    <trim prefix="(" suffix=")" suffixOverrides=",">
      <if test="name != null">
        name,
      </if>
      <if test="password != null">
        password,
      </if>
      <if test="pages != null">
        pages,
      </if>
      <if test="channels != null">
        channels,
      </if>
    </trim>
    <trim prefix="values (" suffix=")" suffixOverrides=",">
      <if test="name != null">
        #{name,jdbcType=VARCHAR},
      </if>
      <if test="password != null">
        #{password,jdbcType=VARCHAR},
      </if>
      <if test="pages != null">
        #{pages,jdbcType=VARCHAR},
      </if>
      <if test="channels != null">
        #{channels,jdbcType=VARCHAR},
      </if>
    </trim>
  </insert>
  <update id="updateByPrimaryKeySelective" parameterType="com.unis.model.Admin">
    <!--
      WARNING - @mbg.generated
      This element is automatically generated by MyBatis Generator, do not modify.
    -->
    update t_backend_admin
    <set>
      <if test="password != null">
        password = #{password,jdbcType=VARCHAR},
      </if>
      <if test="pages != null">
        pages = #{pages,jdbcType=VARCHAR},
      </if>
      <if test="channels != null">
        channels = #{channels,jdbcType=VARCHAR},
      </if>
    </set>
    where name = #{name,jdbcType=VARCHAR}
  </update>
  <update id="updateByPrimaryKey" parameterType="com.unis.model.Admin">
    <!--
      WARNING - @mbg.generated
      This element is automatically generated by MyBatis Generator, do not modify.
    -->
    update t_backend_admin
    set password = #{password,jdbcType=VARCHAR},
      pages = #{pages,jdbcType=VARCHAR},
      channels = #{channels,jdbcType=VARCHAR}
    where name = #{name,jdbcType=VARCHAR}
  </update>
</mapper>